{
  "ticker": "002044",
  "company_name": "美年健康",
  "ingest_date": "2026-03-19",
  "items": [
    {
      "source_type": "news",
      "title": "两融余额七连降 杠杆资金大幅减仓125股",
      "summary": "简称 最新融资余额（亿元） 累计增减（%） 代码 简称 最新融资余额（亿元） 累计增减（%） 603056 德邦股份 0.16 -64.72 688025 杰普特 4.77 131.30 688785 恒运昌 2.38 -63.73 002455 百川股份 4.13 129.61 002044",
      "publish_date": "2026-02-09",
      "available_at": "2026-02-09T09:32:24",
      "sentiment_score": 0.0,
      "category": "其他",
      "urgency": "medium",
      "weight": 1.0,
      "hot_rank": 0
    },
    {
      "source_type": "filing",
      "title": "金证（上海）资产评估有限公司关于深圳证券交易所《关于美年大健康产业控股股份有限公司发行股份购买资产申请的审核问询函》评估相关问题回复之核查意见（修订稿）",
      "summary": "风险事项",
      "publish_date": "2026-02-27",
      "available_at": "2026-02-27T00:00:00",
      "sentiment_score": -0.3,
      "category": "其他",
      "urgency": "medium",
      "weight": 1.15,
      "hot_rank": 0
    },
    {
      "source_type": "filing",
      "title": "美年大健康产业控股股份有限公司审阅报告",
      "summary": "",
      "publish_date": "2026-02-27",
      "available_at": "2026-02-27T00:00:00",
      "sentiment_score": 0.0,
      "category": "其他",
      "urgency": "medium",
      "weight": 1.15,
      "hot_rank": 0
    },
    {
      "source_type": "filing",
      "title": "美年大健康产业控股股份有限公司发行股份购买资产暨关联交易报告书（草案）（二次修订稿）",
      "summary": "",
      "publish_date": "2026-02-27",
      "available_at": "2026-02-27T00:00:00",
      "sentiment_score": 0.0,
      "category": "其他",
      "urgency": "medium",
      "weight": 1.15,
      "hot_rank": 0
    },
    {
      "source_type": "filing",
      "title": "美年大健康产业控股股份有限公司发行股份购买资产暨关联交易报告书（草案）摘要（二次修订稿）",
      "summary": "",
      "publish_date": "2026-02-27",
      "available_at": "2026-02-27T00:00:00",
      "sentiment_score": 0.0,
      "category": "其他",
      "urgency": "medium",
      "weight": 1.15,
      "hot_rank": 0
    },
    {
      "source_type": "filing",
      "title": "美年大健康产业控股股份有限公司关于深圳证券交易所《关于美年大健康产业控股股份有限公司申请发行股份购买资产的审核问询函》之回复（修订稿）",
      "summary": "风险事项",
      "publish_date": "2026-02-27",
      "available_at": "2026-02-27T00:00:00",
      "sentiment_score": -0.3,
      "category": "其他",
      "urgency": "medium",
      "weight": 1.15,
      "hot_rank": 0
    },
    {
      "source_type": "filing",
      "title": "粤开证券股份有限公司关于美年大健康产业控股股份有限公司本次交易摊薄即期回报情况及填补措施的核查意见",
      "summary": "",
      "publish_date": "2026-02-27",
      "available_at": "2026-02-27T00:00:00",
      "sentiment_score": 0.0,
      "category": "其他",
      "urgency": "medium",
      "weight": 1.15,
      "hot_rank": 0
    },
    {
      "source_type": "filing",
      "title": "粤开证券股份有限公司关于美年大健康产业控股股份有限公司发行股份购买资产暨关联交易之独立财务顾问报告（二次修订稿）",
      "summary": "",
      "publish_date": "2026-02-27",
      "available_at": "2026-02-27T00:00:00",
      "sentiment_score": 0.0,
      "category": "其他",
      "urgency": "medium",
      "weight": 1.15,
      "hot_rank": 0
    },
    {
      "source_type": "filing",
      "title": "粤开证券股份有限公司关于深圳证券交易所《关于美年大健康产业控股股份有限公司申请发行股份购买资产的审核问询函》回复之核查意见（修订稿）",
      "summary": "风险事项",
      "publish_date": "2026-02-27",
      "available_at": "2026-02-27T00:00:00",
      "sentiment_score": -0.3,
      "category": "其他",
      "urgency": "medium",
      "weight": 1.15,
      "hot_rank": 0
    },
    {
      "source_type": "filing",
      "title": "第九届董事会第十八次（临时）会议决议公告",
      "summary": "",
      "publish_date": "2026-02-27",
      "available_at": "2026-02-27T00:00:00",
      "sentiment_score": 0.0,
      "category": "其他",
      "urgency": "medium",
      "weight": 1.15,
      "hot_rank": 0
    },
    {
      "source_type": "filing",
      "title": "第九届董事会独立董事专门会议第七次会议审核意见",
      "summary": "",
      "publish_date": "2026-02-27",
      "available_at": "2026-02-27T00:00:00",
      "sentiment_score": 0.0,
      "category": "其他",
      "urgency": "medium",
      "weight": 1.15,
      "hot_rank": 0
    },
    {
      "source_type": "filing",
      "title": "关于向深圳证券交易所申请恢复审核发行股份购买资产暨关联交易的公告",
      "summary": "",
      "publish_date": "2026-02-27",
      "available_at": "2026-02-27T00:00:00",
      "sentiment_score": 0.0,
      "category": "其他",
      "urgency": "medium",
      "weight": 1.15,
      "hot_rank": 0
    },
    {
      "source_type": "filing",
      "title": "关于发行股份购买资产暨关联交易的审核问询函回复更新的提示性公告",
      "summary": "风险事项",
      "publish_date": "2026-02-27",
      "available_at": "2026-02-27T00:00:00",
      "sentiment_score": -0.3,
      "category": "其他",
      "urgency": "medium",
      "weight": 1.15,
      "hot_rank": 0
    },
    {
      "source_type": "filing",
      "title": "关于发行股份购买资产暨关联交易报告书（草案）（修订稿）修订说明的公告",
      "summary": "",
      "publish_date": "2026-02-27",
      "available_at": "2026-02-27T00:00:00",
      "sentiment_score": 0.0,
      "category": "其他",
      "urgency": "medium",
      "weight": 1.15,
      "hot_rank": 0
    },
    {
      "source_type": "filing",
      "title": "公司董事会关于本次交易摊薄即期回报情况及填补措施的说明",
      "summary": "",
      "publish_date": "2026-02-27",
      "available_at": "2026-02-27T00:00:00",
      "sentiment_score": 0.0,
      "category": "其他",
      "urgency": "medium",
      "weight": 1.15,
      "hot_rank": 0
    },
    {
      "source_type": "filing",
      "title": "中审众环会计师事务所（特殊普通合伙）关于美年大健康产业控股股份有限公司《申请发行股份购买资产的审核问询函》的回复（修订稿）",
      "summary": "风险事项",
      "publish_date": "2026-02-27",
      "available_at": "2026-02-27T00:00:00",
      "sentiment_score": -0.3,
      "category": "其他",
      "urgency": "medium",
      "weight": 1.15,
      "hot_rank": 0
    },
    {
      "source_type": "filing",
      "title": "关于收到深圳证券交易所恢复审核发行股份购买资产暨关联交易的公告",
      "summary": "",
      "publish_date": "2026-03-03",
      "available_at": "2026-03-03T00:00:00",
      "sentiment_score": 0.0,
      "category": "其他",
      "urgency": "medium",
      "weight": 1.15,
      "hot_rank": 0
    },
    {
      "source_type": "news",
      "title": "美年健康与阿里健康达成战略合作 共建标准化智能化上门护理服务体系",
      "summary": "3月2日，美年健康（002044.SZ）与阿里健康签署战略合作协议。双方将围绕护理服务协同、线上线下资源整合、医药健康联动三大核心板块，共同打造标准化、智能化的上门护理服务体系，切实提升护理服务的可及性与用户体验。",
      "publish_date": "2026-03-03",
      "available_at": "2026-03-03T16:42:32",
      "sentiment_score": 0.5,
      "category": "重大合同",
      "urgency": "medium",
      "weight": 1.0,
      "hot_rank": 0
    },
    {
      "source_type": "news",
      "title": "解密主力资金出逃股 连续5日净流出502股",
      "summary": "3.33 5.44 -13.74 002664 信质集团 15 3.27 9.98 -15.69 002145 钛能化学 10 3.27 4.95 -0.57 300353 东土科技 9 3.24 5.85 -1.64 601699 潞安环能 5 3.23 6.73 -3.88 002044",
      "publish_date": "2026-03-10",
      "available_at": "2026-03-10T17:42:01",
      "sentiment_score": 0.0,
      "category": "其他",
      "urgency": "medium",
      "weight": 1.0,
      "hot_rank": 0
    }
  ],
  "hot_rank": 0,
  "hot_reason": "",
  "hot_topic_source": "baidu_xueqiu_live"
}