[
  {
    "关键词": "002439",
    "新闻标题": "华为昇腾概念涨3.55%，主力资金净流入49股",
    "新闻内容": "4.90 002777 久远银海 2.33 1.36 363.77 3.61 688207 格灵深瞳 4.33 2.13 349.00 3.98 300872 天阳科技 2.19 3.06 329.62 1.43 002253 *ST智胜 3.09 7.81 285.01 1.52 002439",
    "发布时间": "2026-03-18 17:06:40",
    "文章来源": "证券时报网",
    "新闻链接": "http://finance.eastmoney.com/a/202603183676024095.html",
    "_normalized_publish_date": "2026-03-18"
  },
  {
    "关键词": "002439",
    "新闻标题": "电子身份证概念下跌3.05%，7股主力资金净流出超3000万元",
    "新闻内容": "信安世纪 -5.78 3.53 205.43 301330 熵基科技 0.45 2.65 289.36 688262 国芯科技 -1.71 2.46 358.27 300479 神思电子 -2.39 2.82 799.03 600271 航天信息 -1.46 0.94 1469.68 002439",
    "发布时间": "2026-03-13 17:14:35",
    "文章来源": "证券时报网",
    "新闻链接": "http://finance.eastmoney.com/a/202603133671572341.html",
    "_normalized_publish_date": "2026-03-13"
  },
  {
    "关键词": "002439",
    "新闻标题": "计算机行业今日净流出资金123.92亿元，华胜天成等34股净流出资金超亿元",
    "新闻内容": "0.47 1.02 6972.41 300324 旋极信息 5.66 7.36 6125.63 002405 四维图新 -0.27 5.61 5941.43 300469 信息发展 -0.14 3.81 5341.94 301316 慧博云通 0.53 2.55 4754.18 002439",
    "发布时间": "2026-03-13 16:38:40",
    "文章来源": "证券时报网",
    "新闻链接": "http://finance.eastmoney.com/a/202603133671524790.html",
    "_normalized_publish_date": "2026-03-13"
  }
]